pytorchdbcheckpoint/__init__.py
pytorchdbcheckpoint/checkpointer/__init__.py
pytorchdbcheckpoint/checkpointer/checkpointer.py
pytorchdbcheckpoint/handler/MongoHandler.py
pytorchdbcheckpoint/handler/PostgresHandler.py
pytorchdbcheckpoint/handler/__init__.py
pytorchdbcheckpoint/utils/CheckpointData.py
pytorchdbcheckpoint/utils/HandlerFactory.py
pytorchdbcheckpoint/utils/__init__.py
pytorchdbcheckpoint-0.1.0.dist-info/licenses/LICENSE
pytorchdbcheckpoint-0.1.0.dist-info/METADATA
pytorchdbcheckpoint-0.1.0.dist-info/WHEEL
pytorchdbcheckpoint-0.1.0.dist-info/top_level.txt
pytorchdbcheckpoint-0.1.0.dist-info/RECORD
