Metadata-Version: 2.4
Name: PyTorchDBCheckpoint
Version: 0.1.0
Summary: Checkpoint PyTorch training runs into PostgreSQL database.
Author-email: lakaeso <antonio.lakos1@gmail.com>
License-Expression: MIT
Project-URL: Homepage, https://github.com/lakaeso/pytorch-db-checkpoint
Classifier: Programming Language :: Python :: 3
Classifier: Operating System :: OS Independent
Requires-Python: >=3.9
License-File: LICENSE
Requires-Dist: torch>=2.0.0
Requires-Dist: psycopg2>=2.9.0
Requires-Dist: numpy
Dynamic: license-file
